[
  {
    "version": "2.0.10747-1",
    "deps": {
      "jitsi-videobridge2": "2.3-272-g0360d0488-1",
      "jicofo": "1.0-1169-1",
      "jitsi-meet-web": "1.0.9014-1",
      "jitsi-meet-web-config": "1.0.9014-1",
      "jitsi-meet-prosody": "1.0.9014-1"
    },
    "recommends": {
      "jitsi-meet-turnserver": "1.0.9014-1"
    }
  },
  {
    "version": "2.0.10746-1",
    "deps": {
      "jitsi-videobridge2": "2.3-272-g0360d0488-1",
      "jicofo": "1.0-1169-1",
      "jitsi-meet-web": "1.0.9013-1",
      "jitsi-meet-web-config": "1.0.9013-1",
      "jitsi-meet-prosody": "1.0.9013-1"
    },
    "recommends": {
      "jitsi-meet-turnserver": "1.0.9013-1"
    }
  },
  {
    "version": "2.0.10745-1",
    "deps": {
      "jitsi-videobridge2": "2.3-272-g0360d0488-1",
      "jicofo": "1.0-1169-1",
      "jitsi-meet-web": "1.0.9012-1",
      "jitsi-meet-web-config": "1.0.9012-1",
      "jitsi-meet-prosody": "1.0.9012-1"
    },
    "recommends": {
      "jitsi-meet-turnserver": "1.0.9012-1"
    }
  },
  {
    "version": "2.0.10744-1",
    "deps": {
      "jitsi-videobridge2": "2.3-272-g0360d0488-1",
      "jicofo": "1.0-1169-1",
      "jitsi-meet-web": "1.0.9011-1",
      "jitsi-meet-web-config": "1.0.9011-1",
      "jitsi-meet-prosody": "1.0.9011-1"
    },
    "recommends": {
      "jitsi-meet-turnserver": "1.0.9011-1"
    }
  },
  {
    "version": "2.0.10743-1",
    "deps": {
      "jitsi-videobridge2": "2.3-272-g0360d0488-1",
      "jicofo": "1.0-1169-1",
      "jitsi-meet-web": "1.0.9010-1",
      "jitsi-meet-web-config": "1.0.9010-1",
      "jitsi-meet-prosody": "1.0.9010-1"
    },
    "recommends": {
      "jitsi-meet-turnserver": "1.0.9010-1"
    }
  },
  {
    "version": "2.0.10742-1",
    "deps": {
      "jitsi-videobridge2": "2.3-272-g0360d0488-1",
      "jicofo": "1.0-1169-1",
      "jitsi-meet-web": "1.0.9009-1",
      "jitsi-meet-web-config": "1.0.9009-1",
      "jitsi-meet-prosody": "1.0.9009-1"
    },
    "recommends": {
      "jitsi-meet-turnserver": "1.0.9009-1"
    }
  },
  {
    "version": "2.0.10741-1",
    "deps": {
      "jitsi-videobridge2": "2.3-272-g0360d0488-1",
      "jicofo": "1.0-1169-1",
      "jitsi-meet-web": "1.0.9008-1",
      "jitsi-meet-web-config": "1.0.9008-1",
      "jitsi-meet-prosody": "1.0.9008-1"
    },
    "recommends": {
      "jitsi-meet-turnserver": "1.0.9008-1"
    }
  },
  {
    "version": "2.0.10740-1",
    "deps": {
      "jitsi-videobridge2": "2.3-272-g0360d0488-1",
      "jicofo": "1.0-1169-1",
      "jitsi-meet-web": "1.0.9007-1",
      "jitsi-meet-web-config": "1.0.9007-1",
      "jitsi-meet-prosody": "1.0.9007-1"
    },
    "recommends": {
      "jitsi-meet-turnserver": "1.0.9007-1"
    }
  },
  {
    "version": "2.0.10739-1",
    "deps": {
      "jitsi-videobridge2": "2.3-272-g0360d0488-1",
      "jicofo": "1.0-1169-1",
      "jitsi-meet-web": "1.0.9006-1",
      "jitsi-meet-web-config": "1.0.9006-1",
      "jitsi-meet-prosody": "1.0.9006-1"
    },
    "recommends": {
      "jitsi-meet-turnserver": "1.0.9006-1"
    }
  },
  {
    "version": "2.0.10738-1",
    "deps": {
      "jitsi-videobridge2": "2.3-272-g0360d0488-1",
      "jicofo": "1.0-1169-1",
      "jitsi-meet-web": "1.0.9005-1",
      "jitsi-meet-web-config": "1.0.9005-1",
      "jitsi-meet-prosody": "1.0.9005-1"
    },
    "recommends": {
      "jitsi-meet-turnserver": "1.0.9005-1"
    }
  },
  {
    "version": "2.0.10737-1",
    "deps": {
      "jitsi-videobridge2": "2.3-272-g0360d0488-1",
      "jicofo": "1.0-1169-1",
      "jitsi-meet-web": "1.0.9004-1",
      "jitsi-meet-web-config": "1.0.9004-1",
      "jitsi-meet-prosody": "1.0.9004-1"
    },
    "recommends": {
      "jitsi-meet-turnserver": "1.0.9004-1"
    }
  },
  {
    "version": "2.0.10736-1",
    "deps": {
      "jitsi-videobridge2": "2.3-272-g0360d0488-1",
      "jicofo": "1.0-1169-1",
      "jitsi-meet-web": "1.0.9003-1",
      "jitsi-meet-web-config": "1.0.9003-1",
      "jitsi-meet-prosody": "1.0.9003-1"
    },
    "recommends": {
      "jitsi-meet-turnserver": "1.0.9003-1"
    }
  },
  {
    "version": "2.0.10735-1",
    "deps": {
      "jitsi-videobridge2": "2.3-272-g0360d0488-1",
      "jicofo": "1.0-1169-1",
      "jitsi-meet-web": "1.0.9002-1",
      "jitsi-meet-web-config": "1.0.9002-1",
      "jitsi-meet-prosody": "1.0.9002-1"
    },
    "recommends": {
      "jitsi-meet-turnserver": "1.0.9002-1"
    }
  },
  {
    "version": "2.0.10733-1",
    "deps": {
      "jitsi-videobridge2": "2.3-272-g0360d0488-1",
      "jicofo": "1.0-1169-1",
      "jitsi-meet-web": "1.0.9000-1",
      "jitsi-meet-web-config": "1.0.9000-1",
      "jitsi-meet-prosody": "1.0.9000-1"
    },
    "recommends": {
      "jitsi-meet-turnserver": "1.0.9000-1"
    }
  },
  {
    "version": "2.0.10732-1",
    "deps": {
      "jitsi-videobridge2": "2.3-272-g0360d0488-1",
      "jicofo": "1.0-1169-1",
      "jitsi-meet-web": "1.0.8999-1",
      "jitsi-meet-web-config": "1.0.8999-1",
      "jitsi-meet-prosody": "1.0.8999-1"
    },
    "recommends": {
      "jitsi-meet-turnserver": "1.0.8999-1"
    }
  },
  {
    "version": "2.0.10731-1",
    "deps": {
      "jitsi-videobridge2": "2.3-272-g0360d0488-1",
      "jicofo": "1.0-1169-1",
      "jitsi-meet-web": "1.0.8998-1",
      "jitsi-meet-web-config": "1.0.8998-1",
      "jitsi-meet-prosody": "1.0.8998-1"
    },
    "recommends": {
      "jitsi-meet-turnserver": "1.0.8998-1"
    }
  },
  {
    "version": "2.0.10730-1",
    "deps": {
      "jitsi-videobridge2": "2.3-272-g0360d0488-1",
      "jicofo": "1.0-1169-1",
      "jitsi-meet-web": "1.0.8997-1",
      "jitsi-meet-web-config": "1.0.8997-1",
      "jitsi-meet-prosody": "1.0.8997-1"
    },
    "recommends": {
      "jitsi-meet-turnserver": "1.0.8997-1"
    }
  },
  {
    "version": "2.0.10729-1",
    "deps": {
      "jitsi-videobridge2": "2.3-272-g0360d0488-1",
      "jicofo": "1.0-1169-1",
      "jitsi-meet-web": "1.0.8996-1",
      "jitsi-meet-web-config": "1.0.8996-1",
      "jitsi-meet-prosody": "1.0.8996-1"
    },
    "recommends": {
      "jitsi-meet-turnserver": "1.0.8996-1"
    }
  },
  {
    "version": "2.0.10728-1",
    "deps": {
      "jitsi-videobridge2": "2.3-272-g0360d0488-1",
      "jicofo": "1.0-1169-1",
      "jitsi-meet-web": "1.0.8995-1",
      "jitsi-meet-web-config": "1.0.8995-1",
      "jitsi-meet-prosody": "1.0.8995-1"
    },
    "recommends": {
      "jitsi-meet-turnserver": "1.0.8995-1"
    }
  },
  {
    "version": "2.0.10727-1",
    "deps": {
      "jitsi-videobridge2": "2.3-272-g0360d0488-1",
      "jicofo": "1.0-1169-1",
      "jitsi-meet-web": "1.0.8994-1",
      "jitsi-meet-web-config": "1.0.8994-1",
      "jitsi-meet-prosody": "1.0.8994-1"
    },
    "recommends": {
      "jitsi-meet-turnserver": "1.0.8994-1"
    }
  },
  {
    "version": "2.0.10726-1",
    "deps": {
      "jitsi-videobridge2": "2.3-272-g0360d0488-1",
      "jicofo": "1.0-1169-1",
      "jitsi-meet-web": "1.0.8993-1",
      "jitsi-meet-web-config": "1.0.8993-1",
      "jitsi-meet-prosody": "1.0.8993-1"
    },
    "recommends": {
      "jitsi-meet-turnserver": "1.0.8993-1"
    }
  },
  {
    "version": "2.0.10725-1",
    "deps": {
      "jitsi-videobridge2": "2.3-272-g0360d0488-1",
      "jicofo": "1.0-1169-1",
      "jitsi-meet-web": "1.0.8992-1",
      "jitsi-meet-web-config": "1.0.8992-1",
      "jitsi-meet-prosody": "1.0.8992-1"
    },
    "recommends": {
      "jitsi-meet-turnserver": "1.0.8992-1"
    }
  },
  {
    "version": "2.0.10724-1",
    "deps": {
      "jitsi-videobridge2": "2.3-272-g0360d0488-1",
      "jicofo": "1.0-1169-1",
      "jitsi-meet-web": "1.0.8991-1",
      "jitsi-meet-web-config": "1.0.8991-1",
      "jitsi-meet-prosody": "1.0.8991-1"
    },
    "recommends": {
      "jitsi-meet-turnserver": "1.0.8991-1"
    }
  },
  {
    "version": "2.0.10723-1",
    "deps": {
      "jitsi-videobridge2": "2.3-272-g0360d0488-1",
      "jicofo": "1.0-1169-1",
      "jitsi-meet-web": "1.0.8990-1",
      "jitsi-meet-web-config": "1.0.8990-1",
      "jitsi-meet-prosody": "1.0.8990-1"
    },
    "recommends": {
      "jitsi-meet-turnserver": "1.0.8990-1"
    }
  },
  {
    "version": "2.0.10722-1",
    "deps": {
      "jitsi-videobridge2": "2.3-272-g0360d0488-1",
      "jicofo": "1.0-1169-1",
      "jitsi-meet-web": "1.0.8989-1",
      "jitsi-meet-web-config": "1.0.8989-1",
      "jitsi-meet-prosody": "1.0.8989-1"
    },
    "recommends": {
      "jitsi-meet-turnserver": "1.0.8989-1"
    }
  },
  {
    "version": "2.0.10721-1",
    "deps": {
      "jitsi-videobridge2": "2.3-272-g0360d0488-1",
      "jicofo": "1.0-1169-1",
      "jitsi-meet-web": "1.0.8988-1",
      "jitsi-meet-web-config": "1.0.8988-1",
      "jitsi-meet-prosody": "1.0.8988-1"
    },
    "recommends": {
      "jitsi-meet-turnserver": "1.0.8988-1"
    }
  },
  {
    "version": "2.0.10720-1",
    "deps": {
      "jitsi-videobridge2": "2.3-272-g0360d0488-1",
      "jicofo": "1.0-1169-1",
      "jitsi-meet-web": "1.0.8987-1",
      "jitsi-meet-web-config": "1.0.8987-1",
      "jitsi-meet-prosody": "1.0.8987-1"
    },
    "recommends": {
      "jitsi-meet-turnserver": "1.0.8987-1"
    }
  },
  {
    "version": "2.0.10719-1",
    "deps": {
      "jitsi-videobridge2": "2.3-272-g0360d0488-1",
      "jicofo": "1.0-1169-1",
      "jitsi-meet-web": "1.0.8986-1",
      "jitsi-meet-web-config": "1.0.8986-1",
      "jitsi-meet-prosody": "1.0.8986-1"
    },
    "recommends": {
      "jitsi-meet-turnserver": "1.0.8986-1"
    }
  },
  {
    "version": "2.0.10718-1",
    "deps": {
      "jitsi-videobridge2": "2.3-272-g0360d0488-1",
      "jicofo": "1.0-1169-1",
      "jitsi-meet-web": "1.0.8985-1",
      "jitsi-meet-web-config": "1.0.8985-1",
      "jitsi-meet-prosody": "1.0.8985-1"
    },
    "recommends": {
      "jitsi-meet-turnserver": "1.0.8985-1"
    }
  },
  {
    "version": "2.0.10717-1",
    "deps": {
      "jitsi-videobridge2": "2.3-272-g0360d0488-1",
      "jicofo": "1.0-1169-1",
      "jitsi-meet-web": "1.0.8984-1",
      "jitsi-meet-web-config": "1.0.8984-1",
      "jitsi-meet-prosody": "1.0.8984-1"
    },
    "recommends": {
      "jitsi-meet-turnserver": "1.0.8984-1"
    }
  },
  {
    "version": "2.0.10716-1",
    "deps": {
      "jitsi-videobridge2": "2.3-271-gaaee82264-1",
      "jicofo": "1.0-1169-1",
      "jitsi-meet-web": "1.0.8984-1",
      "jitsi-meet-web-config": "1.0.8984-1",
      "jitsi-meet-prosody": "1.0.8984-1"
    },
    "recommends": {
      "jitsi-meet-turnserver": "1.0.8984-1"
    }
  },
  {
    "version": "2.0.10715-1",
    "deps": {
      "jitsi-videobridge2": "2.3-271-gaaee82264-1",
      "jicofo": "1.0-1169-1",
      "jitsi-meet-web": "1.0.8983-1",
      "jitsi-meet-web-config": "1.0.8983-1",
      "jitsi-meet-prosody": "1.0.8983-1"
    },
    "recommends": {
      "jitsi-meet-turnserver": "1.0.8983-1"
    }
  },
  {
    "version": "2.0.10714-1",
    "deps": {
      "jitsi-videobridge2": "2.3-271-gaaee82264-1",
      "jicofo": "1.0-1169-1",
      "jitsi-meet-web": "1.0.8982-1",
      "jitsi-meet-web-config": "1.0.8982-1",
      "jitsi-meet-prosody": "1.0.8982-1"
    },
    "recommends": {
      "jitsi-meet-turnserver": "1.0.8982-1"
    }
  },
  {
    "version": "2.0.10713-1",
    "deps": {
      "jitsi-videobridge2": "2.3-270-g38ea5ea44-1",
      "jicofo": "1.0-1169-1",
      "jitsi-meet-web": "1.0.8982-1",
      "jitsi-meet-web-config": "1.0.8982-1",
      "jitsi-meet-prosody": "1.0.8982-1"
    },
    "recommends": {
      "jitsi-meet-turnserver": "1.0.8982-1"
    }
  },
  {
    "version": "2.0.10712-1",
    "deps": {
      "jitsi-videobridge2": "2.3-270-g38ea5ea44-1",
      "jicofo": "1.0-1169-1",
      "jitsi-meet-web": "1.0.8981-1",
      "jitsi-meet-web-config": "1.0.8981-1",
      "jitsi-meet-prosody": "1.0.8981-1"
    },
    "recommends": {
      "jitsi-meet-turnserver": "1.0.8981-1"
    }
  },
  {
    "version": "2.0.10711-1",
    "deps": {
      "jitsi-videobridge2": "2.3-270-g38ea5ea44-1",
      "jicofo": "1.0-1169-1",
      "jitsi-meet-web": "1.0.8980-1",
      "jitsi-meet-web-config": "1.0.8980-1",
      "jitsi-meet-prosody": "1.0.8980-1"
    },
    "recommends": {
      "jitsi-meet-turnserver": "1.0.8980-1"
    }
  },
  {
    "version": "2.0.10710-1",
    "deps": {
      "jitsi-videobridge2": "2.3-270-g38ea5ea44-1",
      "jicofo": "1.0-1169-1",
      "jitsi-meet-web": "1.0.8979-1",
      "jitsi-meet-web-config": "1.0.8979-1",
      "jitsi-meet-prosody": "1.0.8979-1"
    },
    "recommends": {
      "jitsi-meet-turnserver": "1.0.8979-1"
    }
  },
  {
    "version": "2.0.10709-1",
    "deps": {
      "jitsi-videobridge2": "2.3-270-g38ea5ea44-1",
      "jicofo": "1.0-1169-1",
      "jitsi-meet-web": "1.0.8978-1",
      "jitsi-meet-web-config": "1.0.8978-1",
      "jitsi-meet-prosody": "1.0.8978-1"
    },
    "recommends": {
      "jitsi-meet-turnserver": "1.0.8978-1"
    }
  },
  {
    "version": "2.0.10708-1",
    "deps": {
      "jitsi-videobridge2": "2.3-269-g57402c53a-1",
      "jicofo": "1.0-1169-1",
      "jitsi-meet-web": "1.0.8978-1",
      "jitsi-meet-web-config": "1.0.8978-1",
      "jitsi-meet-prosody": "1.0.8978-1"
    },
    "recommends": {
      "jitsi-meet-turnserver": "1.0.8978-1"
    }
  },
  {
    "version": "2.0.10707-1",
    "deps": {
      "jitsi-videobridge2": "2.3-269-g57402c53a-1",
      "jicofo": "1.0-1169-1",
      "jitsi-meet-web": "1.0.8977-1",
      "jitsi-meet-web-config": "1.0.8977-1",
      "jitsi-meet-prosody": "1.0.8977-1"
    },
    "recommends": {
      "jitsi-meet-turnserver": "1.0.8977-1"
    }
  },
  {
    "version": "2.0.10706-1",
    "deps": {
      "jitsi-videobridge2": "2.3-269-g57402c53a-1",
      "jicofo": "1.0-1169-1",
      "jitsi-meet-web": "1.0.8976-1",
      "jitsi-meet-web-config": "1.0.8976-1",
      "jitsi-meet-prosody": "1.0.8976-1"
    },
    "recommends": {
      "jitsi-meet-turnserver": "1.0.8976-1"
    }
  },
  {
    "version": "2.0.10705-1",
    "deps": {
      "jitsi-videobridge2": "2.3-269-g57402c53a-1",
      "jicofo": "1.0-1169-1",
      "jitsi-meet-web": "1.0.8975-1",
      "jitsi-meet-web-config": "1.0.8975-1",
      "jitsi-meet-prosody": "1.0.8975-1"
    },
    "recommends": {
      "jitsi-meet-turnserver": "1.0.8975-1"
    }
  },
  {
    "version": "2.0.10704-1",
    "deps": {
      "jitsi-videobridge2": "2.3-269-g57402c53a-1",
      "jicofo": "1.0-1169-1",
      "jitsi-meet-web": "1.0.8974-1",
      "jitsi-meet-web-config": "1.0.8974-1",
      "jitsi-meet-prosody": "1.0.8974-1"
    },
    "recommends": {
      "jitsi-meet-turnserver": "1.0.8974-1"
    }
  },
  {
    "version": "2.0.10703-1",
    "deps": {
      "jitsi-videobridge2": "2.3-268-gd73cf531b-1",
      "jicofo": "1.0-1169-1",
      "jitsi-meet-web": "1.0.8974-1",
      "jitsi-meet-web-config": "1.0.8974-1",
      "jitsi-meet-prosody": "1.0.8974-1"
    },
    "recommends": {
      "jitsi-meet-turnserver": "1.0.8974-1"
    }
  },
  {
    "version": "2.0.10702-1",
    "deps": {
      "jitsi-videobridge2": "2.3-268-gd73cf531b-1",
      "jicofo": "1.0-1169-1",
      "jitsi-meet-web": "1.0.8973-1",
      "jitsi-meet-web-config": "1.0.8973-1",
      "jitsi-meet-prosody": "1.0.8973-1"
    },
    "recommends": {
      "jitsi-meet-turnserver": "1.0.8973-1"
    }
  },
  {
    "version": "2.0.10701-1",
    "deps": {
      "jitsi-videobridge2": "2.3-268-gd73cf531b-1",
      "jicofo": "1.0-1169-1",
      "jitsi-meet-web": "1.0.8972-1",
      "jitsi-meet-web-config": "1.0.8972-1",
      "jitsi-meet-prosody": "1.0.8972-1"
    },
    "recommends": {
      "jitsi-meet-turnserver": "1.0.8972-1"
    }
  },
  {
    "version": "2.0.10700-1",
    "deps": {
      "jitsi-videobridge2": "2.3-268-gd73cf531b-1",
      "jicofo": "1.0-1168-1",
      "jitsi-meet-web": "1.0.8972-1",
      "jitsi-meet-web-config": "1.0.8972-1",
      "jitsi-meet-prosody": "1.0.8972-1"
    },
    "recommends": {
      "jitsi-meet-turnserver": "1.0.8972-1"
    }
  },
  {
    "version": "2.0.10699-1",
    "deps": {
      "jitsi-videobridge2": "2.3-268-gd73cf531b-1",
      "jicofo": "1.0-1168-1",
      "jitsi-meet-web": "1.0.8971-1",
      "jitsi-meet-web-config": "1.0.8971-1",
      "jitsi-meet-prosody": "1.0.8971-1"
    },
    "recommends": {
      "jitsi-meet-turnserver": "1.0.8971-1"
    }
  },
  {
    "version": "2.0.10698-1",
    "deps": {
      "jitsi-videobridge2": "2.3-268-gd73cf531b-1",
      "jicofo": "1.0-1168-1",
      "jitsi-meet-web": "1.0.8970-1",
      "jitsi-meet-web-config": "1.0.8970-1",
      "jitsi-meet-prosody": "1.0.8970-1"
    },
    "recommends": {
      "jitsi-meet-turnserver": "1.0.8970-1"
    }
  },
  {
    "version": "2.0.10697-1",
    "deps": {
      "jitsi-videobridge2": "2.3-268-gd73cf531b-1",
      "jicofo": "1.0-1168-1",
      "jitsi-meet-web": "1.0.8969-1",
      "jitsi-meet-web-config": "1.0.8969-1",
      "jitsi-meet-prosody": "1.0.8969-1"
    },
    "recommends": {
      "jitsi-meet-turnserver": "1.0.8969-1"
    }
  },
  {
    "version": "2.0.10696-1",
    "deps": {
      "jitsi-videobridge2": "2.3-268-gd73cf531b-1",
      "jicofo": "1.0-1168-1",
      "jitsi-meet-web": "1.0.8968-1",
      "jitsi-meet-web-config": "1.0.8968-1",
      "jitsi-meet-prosody": "1.0.8968-1"
    },
    "recommends": {
      "jitsi-meet-turnserver": "1.0.8968-1"
    }
  },
  {
    "version": "2.0.10695-1",
    "deps": {
      "jitsi-videobridge2": "2.3-268-gd73cf531b-1",
      "jicofo": "1.0-1168-1",
      "jitsi-meet-web": "1.0.8967-1",
      "jitsi-meet-web-config": "1.0.8967-1",
      "jitsi-meet-prosody": "1.0.8967-1"
    },
    "recommends": {
      "jitsi-meet-turnserver": "1.0.8967-1"
    }
  },
  {
    "version": "2.0.10694-1",
    "deps": {
      "jitsi-videobridge2": "2.3-268-gd73cf531b-1",
      "jicofo": "1.0-1168-1",
      "jitsi-meet-web": "1.0.8966-1",
      "jitsi-meet-web-config": "1.0.8966-1",
      "jitsi-meet-prosody": "1.0.8966-1"
    },
    "recommends": {
      "jitsi-meet-turnserver": "1.0.8966-1"
    }
  },
  {
    "version": "2.0.10693-1",
    "deps": {
      "jitsi-videobridge2": "2.3-268-gd73cf531b-1",
      "jicofo": "1.0-1168-1",
      "jitsi-meet-web": "1.0.8965-1",
      "jitsi-meet-web-config": "1.0.8965-1",
      "jitsi-meet-prosody": "1.0.8965-1"
    },
    "recommends": {
      "jitsi-meet-turnserver": "1.0.8965-1"
    }
  },
  {
    "version": "2.0.10692-1",
    "deps": {
      "jitsi-videobridge2": "2.3-268-gd73cf531b-1",
      "jicofo": "1.0-1168-1",
      "jitsi-meet-web": "1.0.8964-1",
      "jitsi-meet-web-config": "1.0.8964-1",
      "jitsi-meet-prosody": "1.0.8964-1"
    },
    "recommends": {
      "jitsi-meet-turnserver": "1.0.8964-1"
    }
  },
  {
    "version": "2.0.10691-1",
    "deps": {
      "jitsi-videobridge2": "2.3-267-g1db58f41a-1",
      "jicofo": "1.0-1168-1",
      "jitsi-meet-web": "1.0.8964-1",
      "jitsi-meet-web-config": "1.0.8964-1",
      "jitsi-meet-prosody": "1.0.8964-1"
    },
    "recommends": {
      "jitsi-meet-turnserver": "1.0.8964-1"
    }
  },
  {
    "version": "2.0.10690-1",
    "deps": {
      "jitsi-videobridge2": "2.3-267-g1db58f41a-1",
      "jicofo": "1.0-1168-1",
      "jitsi-meet-web": "1.0.8963-1",
      "jitsi-meet-web-config": "1.0.8963-1",
      "jitsi-meet-prosody": "1.0.8963-1"
    },
    "recommends": {
      "jitsi-meet-turnserver": "1.0.8963-1"
    }
  },
  {
    "version": "2.0.10689-1",
    "deps": {
      "jitsi-videobridge2": "2.3-266-g19d480681-1",
      "jicofo": "1.0-1168-1",
      "jitsi-meet-web": "1.0.8963-1",
      "jitsi-meet-web-config": "1.0.8963-1",
      "jitsi-meet-prosody": "1.0.8963-1"
    },
    "recommends": {
      "jitsi-meet-turnserver": "1.0.8963-1"
    }
  },
  {
    "version": "2.0.10688-1",
    "deps": {
      "jitsi-videobridge2": "2.3-266-g19d480681-1",
      "jicofo": "1.0-1168-1",
      "jitsi-meet-web": "1.0.8962-1",
      "jitsi-meet-web-config": "1.0.8962-1",
      "jitsi-meet-prosody": "1.0.8962-1"
    },
    "recommends": {
      "jitsi-meet-turnserver": "1.0.8962-1"
    }
  },
  {
    "version": "2.0.10687-1",
    "deps": {
      "jitsi-videobridge2": "2.3-265-g2afd9a4c3-1",
      "jicofo": "1.0-1168-1",
      "jitsi-meet-web": "1.0.8962-1",
      "jitsi-meet-web-config": "1.0.8962-1",
      "jitsi-meet-prosody": "1.0.8962-1"
    },
    "recommends": {
      "jitsi-meet-turnserver": "1.0.8962-1"
    }
  },
  {
    "version": "2.0.10686-1",
    "deps": {
      "jitsi-videobridge2": "2.3-264-g89cd46ab1-1",
      "jicofo": "1.0-1168-1",
      "jitsi-meet-web": "1.0.8962-1",
      "jitsi-meet-web-config": "1.0.8962-1",
      "jitsi-meet-prosody": "1.0.8962-1"
    },
    "recommends": {
      "jitsi-meet-turnserver": "1.0.8962-1"
    }
  },
  {
    "version": "2.0.10685-1",
    "deps": {
      "jitsi-videobridge2": "2.3-264-g89cd46ab1-1",
      "jicofo": "1.0-1168-1",
      "jitsi-meet-web": "1.0.8961-1",
      "jitsi-meet-web-config": "1.0.8961-1",
      "jitsi-meet-prosody": "1.0.8961-1"
    },
    "recommends": {
      "jitsi-meet-turnserver": "1.0.8961-1"
    }
  },
  {
    "version": "2.0.10684-1",
    "deps": {
      "jitsi-videobridge2": "2.3-264-g89cd46ab1-1",
      "jicofo": "1.0-1168-1",
      "jitsi-meet-web": "1.0.8960-1",
      "jitsi-meet-web-config": "1.0.8960-1",
      "jitsi-meet-prosody": "1.0.8960-1"
    },
    "recommends": {
      "jitsi-meet-turnserver": "1.0.8960-1"
    }
  },
  {
    "version": "2.0.10683-1",
    "deps": {
      "jitsi-videobridge2": "2.3-264-g89cd46ab1-1",
      "jicofo": "1.0-1168-1",
      "jitsi-meet-web": "1.0.8959-1",
      "jitsi-meet-web-config": "1.0.8959-1",
      "jitsi-meet-prosody": "1.0.8959-1"
    },
    "recommends": {
      "jitsi-meet-turnserver": "1.0.8959-1"
    }
  },
  {
    "version": "2.0.10682-1",
    "deps": {
      "jitsi-videobridge2": "2.3-264-g89cd46ab1-1",
      "jicofo": "1.0-1168-1",
      "jitsi-meet-web": "1.0.8958-1",
      "jitsi-meet-web-config": "1.0.8958-1",
      "jitsi-meet-prosody": "1.0.8958-1"
    },
    "recommends": {
      "jitsi-meet-turnserver": "1.0.8958-1"
    }
  },
  {
    "version": "2.0.10681-1",
    "deps": {
      "jitsi-videobridge2": "2.3-264-g89cd46ab1-1",
      "jicofo": "1.0-1168-1",
      "jitsi-meet-web": "1.0.8957-1",
      "jitsi-meet-web-config": "1.0.8957-1",
      "jitsi-meet-prosody": "1.0.8957-1"
    },
    "recommends": {
      "jitsi-meet-turnserver": "1.0.8957-1"
    }
  },
  {
    "version": "2.0.10680-1",
    "deps": {
      "jitsi-videobridge2": "2.3-263-gb3ef81e0f-1",
      "jicofo": "1.0-1168-1",
      "jitsi-meet-web": "1.0.8957-1",
      "jitsi-meet-web-config": "1.0.8957-1",
      "jitsi-meet-prosody": "1.0.8957-1"
    },
    "recommends": {
      "jitsi-meet-turnserver": "1.0.8957-1"
    }
  },
  {
    "version": "2.0.10679-1",
    "deps": {
      "jitsi-videobridge2": "2.3-262-gd2dc4df00-1",
      "jicofo": "1.0-1168-1",
      "jitsi-meet-web": "1.0.8957-1",
      "jitsi-meet-web-config": "1.0.8957-1",
      "jitsi-meet-prosody": "1.0.8957-1"
    },
    "recommends": {
      "jitsi-meet-turnserver": "1.0.8957-1"
    }
  },
  {
    "version": "2.0.10678-1",
    "deps": {
      "jitsi-videobridge2": "2.3-262-gd2dc4df00-1",
      "jicofo": "1.0-1167-1",
      "jitsi-meet-web": "1.0.8957-1",
      "jitsi-meet-web-config": "1.0.8957-1",
      "jitsi-meet-prosody": "1.0.8957-1"
    },
    "recommends": {
      "jitsi-meet-turnserver": "1.0.8957-1"
    }
  },
  {
    "version": "2.0.10677-1",
    "deps": {
      "jitsi-videobridge2": "2.3-262-gd2dc4df00-1",
      "jicofo": "1.0-1167-1",
      "jitsi-meet-web": "1.0.8956-1",
      "jitsi-meet-web-config": "1.0.8956-1",
      "jitsi-meet-prosody": "1.0.8956-1"
    },
    "recommends": {
      "jitsi-meet-turnserver": "1.0.8956-1"
    }
  },
  {
    "version": "2.0.10676-1",
    "deps": {
      "jitsi-videobridge2": "2.3-262-gd2dc4df00-1",
      "jicofo": "1.0-1167-1",
      "jitsi-meet-web": "1.0.8955-1",
      "jitsi-meet-web-config": "1.0.8955-1",
      "jitsi-meet-prosody": "1.0.8955-1"
    },
    "recommends": {
      "jitsi-meet-turnserver": "1.0.8955-1"
    }
  },
  {
    "version": "2.0.10675-1",
    "deps": {
      "jitsi-videobridge2": "2.3-262-gd2dc4df00-1",
      "jicofo": "1.0-1167-1",
      "jitsi-meet-web": "1.0.8954-1",
      "jitsi-meet-web-config": "1.0.8954-1",
      "jitsi-meet-prosody": "1.0.8954-1"
    },
    "recommends": {
      "jitsi-meet-turnserver": "1.0.8954-1"
    }
  },
  {
    "version": "2.0.10674-1",
    "deps": {
      "jitsi-videobridge2": "2.3-262-gd2dc4df00-1",
      "jicofo": "1.0-1167-1",
      "jitsi-meet-web": "1.0.8953-1",
      "jitsi-meet-web-config": "1.0.8953-1",
      "jitsi-meet-prosody": "1.0.8953-1"
    },
    "recommends": {
      "jitsi-meet-turnserver": "1.0.8953-1"
    }
  },
  {
    "version": "2.0.10673-1",
    "deps": {
      "jitsi-videobridge2": "2.3-262-gd2dc4df00-1",
      "jicofo": "1.0-1167-1",
      "jitsi-meet-web": "1.0.8952-1",
      "jitsi-meet-web-config": "1.0.8952-1",
      "jitsi-meet-prosody": "1.0.8952-1"
    },
    "recommends": {
      "jitsi-meet-turnserver": "1.0.8952-1"
    }
  },
  {
    "version": "2.0.10672-1",
    "deps": {
      "jitsi-videobridge2": "2.3-262-gd2dc4df00-1",
      "jicofo": "1.0-1167-1",
      "jitsi-meet-web": "1.0.8951-1",
      "jitsi-meet-web-config": "1.0.8951-1",
      "jitsi-meet-prosody": "1.0.8951-1"
    },
    "recommends": {
      "jitsi-meet-turnserver": "1.0.8951-1"
    }
  },
  {
    "version": "2.0.10671-1",
    "deps": {
      "jitsi-videobridge2": "2.3-262-gd2dc4df00-1",
      "jicofo": "1.0-1167-1",
      "jitsi-meet-web": "1.0.8950-1",
      "jitsi-meet-web-config": "1.0.8950-1",
      "jitsi-meet-prosody": "1.0.8950-1"
    },
    "recommends": {
      "jitsi-meet-turnserver": "1.0.8950-1"
    }
  },
  {
    "version": "2.0.10670-1",
    "deps": {
      "jitsi-videobridge2": "2.3-262-gd2dc4df00-1",
      "jicofo": "1.0-1167-1",
      "jitsi-meet-web": "1.0.8949-1",
      "jitsi-meet-web-config": "1.0.8949-1",
      "jitsi-meet-prosody": "1.0.8949-1"
    },
    "recommends": {
      "jitsi-meet-turnserver": "1.0.8949-1"
    }
  },
  {
    "version": "2.0.10669-1",
    "deps": {
      "jitsi-videobridge2": "2.3-262-gd2dc4df00-1",
      "jicofo": "1.0-1167-1",
      "jitsi-meet-web": "1.0.8948-1",
      "jitsi-meet-web-config": "1.0.8948-1",
      "jitsi-meet-prosody": "1.0.8948-1"
    },
    "recommends": {
      "jitsi-meet-turnserver": "1.0.8948-1"
    }
  },
  {
    "version": "2.0.10668-1",
    "deps": {
      "jitsi-videobridge2": "2.3-262-gd2dc4df00-1",
      "jicofo": "1.0-1167-1",
      "jitsi-meet-web": "1.0.8947-1",
      "jitsi-meet-web-config": "1.0.8947-1",
      "jitsi-meet-prosody": "1.0.8947-1"
    },
    "recommends": {
      "jitsi-meet-turnserver": "1.0.8947-1"
    }
  },
  {
    "version": "2.0.10667-1",
    "deps": {
      "jitsi-videobridge2": "2.3-262-gd2dc4df00-1",
      "jicofo": "1.0-1167-1",
      "jitsi-meet-web": "1.0.8946-1",
      "jitsi-meet-web-config": "1.0.8946-1",
      "jitsi-meet-prosody": "1.0.8946-1"
    },
    "recommends": {
      "jitsi-meet-turnserver": "1.0.8946-1"
    }
  },
  {
    "version": "2.0.10666-1",
    "deps": {
      "jitsi-videobridge2": "2.3-261-ge072fe9aa-1",
      "jicofo": "1.0-1167-1",
      "jitsi-meet-web": "1.0.8946-1",
      "jitsi-meet-web-config": "1.0.8946-1",
      "jitsi-meet-prosody": "1.0.8946-1"
    },
    "recommends": {
      "jitsi-meet-turnserver": "1.0.8946-1"
    }
  },
  {
    "version": "2.0.10665-1",
    "deps": {
      "jitsi-videobridge2": "2.3-260-gea11cd36c-1",
      "jicofo": "1.0-1167-1",
      "jitsi-meet-web": "1.0.8946-1",
      "jitsi-meet-web-config": "1.0.8946-1",
      "jitsi-meet-prosody": "1.0.8946-1"
    },
    "recommends": {
      "jitsi-meet-turnserver": "1.0.8946-1"
    }
  },
  {
    "version": "2.0.10664-1",
    "deps": {
      "jitsi-videobridge2": "2.3-260-gea11cd36c-1",
      "jicofo": "1.0-1167-1",
      "jitsi-meet-web": "1.0.8945-1",
      "jitsi-meet-web-config": "1.0.8945-1",
      "jitsi-meet-prosody": "1.0.8945-1"
    },
    "recommends": {
      "jitsi-meet-turnserver": "1.0.8945-1"
    }
  },
  {
    "version": "2.0.10663-1",
    "deps": {
      "jitsi-videobridge2": "2.3-260-gea11cd36c-1",
      "jicofo": "1.0-1167-1",
      "jitsi-meet-web": "1.0.8944-1",
      "jitsi-meet-web-config": "1.0.8944-1",
      "jitsi-meet-prosody": "1.0.8944-1"
    },
    "recommends": {
      "jitsi-meet-turnserver": "1.0.8944-1"
    }
  },
  {
    "version": "2.0.10662-1",
    "deps": {
      "jitsi-videobridge2": "2.3-260-gea11cd36c-1",
      "jicofo": "1.0-1167-1",
      "jitsi-meet-web": "1.0.8943-1",
      "jitsi-meet-web-config": "1.0.8943-1",
      "jitsi-meet-prosody": "1.0.8943-1"
    },
    "recommends": {
      "jitsi-meet-turnserver": "1.0.8943-1"
    }
  },
  {
    "version": "2.0.10661-1",
    "deps": {
      "jitsi-videobridge2": "2.3-260-gea11cd36c-1",
      "jicofo": "1.0-1167-1",
      "jitsi-meet-web": "1.0.8942-1",
      "jitsi-meet-web-config": "1.0.8942-1",
      "jitsi-meet-prosody": "1.0.8942-1"
    },
    "recommends": {
      "jitsi-meet-turnserver": "1.0.8942-1"
    }
  },
  {
    "version": "2.0.10660-1",
    "deps": {
      "jitsi-videobridge2": "2.3-260-gea11cd36c-1",
      "jicofo": "1.0-1167-1",
      "jitsi-meet-web": "1.0.8941-1",
      "jitsi-meet-web-config": "1.0.8941-1",
      "jitsi-meet-prosody": "1.0.8941-1"
    },
    "recommends": {
      "jitsi-meet-turnserver": "1.0.8941-1"
    }
  },
  {
    "version": "2.0.10659-1",
    "deps": {
      "jitsi-videobridge2": "2.3-260-gea11cd36c-1",
      "jicofo": "1.0-1167-1",
      "jitsi-meet-web": "1.0.8940-1",
      "jitsi-meet-web-config": "1.0.8940-1",
      "jitsi-meet-prosody": "1.0.8940-1"
    },
    "recommends": {
      "jitsi-meet-turnserver": "1.0.8940-1"
    }
  },
  {
    "version": "2.0.10658-1",
    "deps": {
      "jitsi-videobridge2": "2.3-260-gea11cd36c-1",
      "jicofo": "1.0-1167-1",
      "jitsi-meet-web": "1.0.8939-1",
      "jitsi-meet-web-config": "1.0.8939-1",
      "jitsi-meet-prosody": "1.0.8939-1"
    },
    "recommends": {
      "jitsi-meet-turnserver": "1.0.8939-1"
    }
  },
  {
    "version": "2.0.10657-1",
    "deps": {
      "jitsi-videobridge2": "2.3-260-gea11cd36c-1",
      "jicofo": "1.0-1167-1",
      "jitsi-meet-web": "1.0.8938-1",
      "jitsi-meet-web-config": "1.0.8938-1",
      "jitsi-meet-prosody": "1.0.8938-1"
    },
    "recommends": {
      "jitsi-meet-turnserver": "1.0.8938-1"
    }
  },
  {
    "version": "2.0.10656-1",
    "deps": {
      "jitsi-videobridge2": "2.3-260-gea11cd36c-1",
      "jicofo": "1.0-1167-1",
      "jitsi-meet-web": "1.0.8937-1",
      "jitsi-meet-web-config": "1.0.8937-1",
      "jitsi-meet-prosody": "1.0.8937-1"
    },
    "recommends": {
      "jitsi-meet-turnserver": "1.0.8937-1"
    }
  },
  {
    "version": "2.0.10655-1",
    "deps": {
      "jitsi-videobridge2": "2.3-260-gea11cd36c-1",
      "jicofo": "1.0-1167-1",
      "jitsi-meet-web": "1.0.8936-1",
      "jitsi-meet-web-config": "1.0.8936-1",
      "jitsi-meet-prosody": "1.0.8936-1"
    },
    "recommends": {
      "jitsi-meet-turnserver": "1.0.8936-1"
    }
  },
  {
    "version": "2.0.10654-1",
    "deps": {
      "jitsi-videobridge2": "2.3-260-gea11cd36c-1",
      "jicofo": "1.0-1167-1",
      "jitsi-meet-web": "1.0.8934-1",
      "jitsi-meet-web-config": "1.0.8934-1",
      "jitsi-meet-prosody": "1.0.8934-1"
    },
    "recommends": {
      "jitsi-meet-turnserver": "1.0.8934-1"
    }
  },
  {
    "version": "2.0.10653-1",
    "deps": {
      "jitsi-videobridge2": "2.3-260-gea11cd36c-1",
      "jicofo": "1.0-1167-1",
      "jitsi-meet-web": "1.0.8933-1",
      "jitsi-meet-web-config": "1.0.8933-1",
      "jitsi-meet-prosody": "1.0.8933-1"
    },
    "recommends": {
      "jitsi-meet-turnserver": "1.0.8933-1"
    }
  },
  {
    "version": "2.0.10652-1",
    "deps": {
      "jitsi-videobridge2": "2.3-260-gea11cd36c-1",
      "jicofo": "1.0-1167-1",
      "jitsi-meet-web": "1.0.8932-1",
      "jitsi-meet-web-config": "1.0.8932-1",
      "jitsi-meet-prosody": "1.0.8932-1"
    },
    "recommends": {
      "jitsi-meet-turnserver": "1.0.8932-1"
    }
  },
  {
    "version": "2.0.10651-1",
    "deps": {
      "jitsi-videobridge2": "2.3-260-gea11cd36c-1",
      "jicofo": "1.0-1167-1",
      "jitsi-meet-web": "1.0.8931-1",
      "jitsi-meet-web-config": "1.0.8931-1",
      "jitsi-meet-prosody": "1.0.8931-1"
    },
    "recommends": {
      "jitsi-meet-turnserver": "1.0.8931-1"
    }
  },
  {
    "version": "2.0.10650-1",
    "deps": {
      "jitsi-videobridge2": "2.3-260-gea11cd36c-1",
      "jicofo": "1.0-1167-1",
      "jitsi-meet-web": "1.0.8930-1",
      "jitsi-meet-web-config": "1.0.8930-1",
      "jitsi-meet-prosody": "1.0.8930-1"
    },
    "recommends": {
      "jitsi-meet-turnserver": "1.0.8930-1"
    }
  },
  {
    "version": "2.0.10649-1",
    "deps": {
      "jitsi-videobridge2": "2.3-260-gea11cd36c-1",
      "jicofo": "1.0-1167-1",
      "jitsi-meet-web": "1.0.8929-1",
      "jitsi-meet-web-config": "1.0.8929-1",
      "jitsi-meet-prosody": "1.0.8929-1"
    },
    "recommends": {
      "jitsi-meet-turnserver": "1.0.8929-1"
    }
  },
  {
    "version": "2.0.10648-1",
    "deps": {
      "jitsi-videobridge2": "2.3-260-gea11cd36c-1",
      "jicofo": "1.0-1167-1",
      "jitsi-meet-web": "1.0.8928-1",
      "jitsi-meet-web-config": "1.0.8928-1",
      "jitsi-meet-prosody": "1.0.8928-1"
    },
    "recommends": {
      "jitsi-meet-turnserver": "1.0.8928-1"
    }
  },
  {
    "version": "2.0.10647-1",
    "deps": {
      "jitsi-videobridge2": "2.3-260-gea11cd36c-1",
      "jicofo": "1.0-1167-1",
      "jitsi-meet-web": "1.0.8927-1",
      "jitsi-meet-web-config": "1.0.8927-1",
      "jitsi-meet-prosody": "1.0.8927-1"
    },
    "recommends": {
      "jitsi-meet-turnserver": "1.0.8927-1"
    }
  },
  {
    "version": "2.0.10646-1",
    "deps": {
      "jitsi-videobridge2": "2.3-260-gea11cd36c-1",
      "jicofo": "1.0-1167-1",
      "jitsi-meet-web": "1.0.8926-1",
      "jitsi-meet-web-config": "1.0.8926-1",
      "jitsi-meet-prosody": "1.0.8926-1"
    },
    "recommends": {
      "jitsi-meet-turnserver": "1.0.8926-1"
    }
  },
  {
    "version": "2.0.10644-1",
    "deps": {
      "jitsi-videobridge2": "2.3-260-gea11cd36c-1",
      "jicofo": "1.0-1167-1",
      "jitsi-meet-web": "1.0.8925-1",
      "jitsi-meet-web-config": "1.0.8925-1",
      "jitsi-meet-prosody": "1.0.8925-1"
    },
    "recommends": {
      "jitsi-meet-turnserver": "1.0.8925-1"
    }
  },
  {
    "version": "2.0.10643-1",
    "deps": {
      "jitsi-videobridge2": "2.3-260-gea11cd36c-1",
      "jicofo": "1.0-1167-1",
      "jitsi-meet-web": "1.0.8924-1",
      "jitsi-meet-web-config": "1.0.8924-1",
      "jitsi-meet-prosody": "1.0.8924-1"
    },
    "recommends": {
      "jitsi-meet-turnserver": "1.0.8924-1"
    }
  },
  {
    "version": "2.0.10642-1",
    "deps": {
      "jitsi-videobridge2": "2.3-260-gea11cd36c-1",
      "jicofo": "1.0-1167-1",
      "jitsi-meet-web": "1.0.8923-1",
      "jitsi-meet-web-config": "1.0.8923-1",
      "jitsi-meet-prosody": "1.0.8923-1"
    },
    "recommends": {
      "jitsi-meet-turnserver": "1.0.8923-1"
    }
  },
  {
    "version": "2.0.10641-1",
    "deps": {
      "jitsi-videobridge2": "2.3-260-gea11cd36c-1",
      "jicofo": "1.0-1167-1",
      "jitsi-meet-web": "1.0.8922-1",
      "jitsi-meet-web-config": "1.0.8922-1",
      "jitsi-meet-prosody": "1.0.8922-1"
    },
    "recommends": {
      "jitsi-meet-turnserver": "1.0.8922-1"
    }
  },
  {
    "version": "2.0.10640-1",
    "deps": {
      "jitsi-videobridge2": "2.3-260-gea11cd36c-1",
      "jicofo": "1.0-1167-1",
      "jitsi-meet-web": "1.0.8921-1",
      "jitsi-meet-web-config": "1.0.8921-1",
      "jitsi-meet-prosody": "1.0.8921-1"
    },
    "recommends": {
      "jitsi-meet-turnserver": "1.0.8921-1"
    }
  },
  {
    "version": "2.0.10639-1",
    "deps": {
      "jitsi-videobridge2": "2.3-260-gea11cd36c-1",
      "jicofo": "1.0-1167-1",
      "jitsi-meet-web": "1.0.8920-1",
      "jitsi-meet-web-config": "1.0.8920-1",
      "jitsi-meet-prosody": "1.0.8920-1"
    },
    "recommends": {
      "jitsi-meet-turnserver": "1.0.8920-1"
    }
  },
  {
    "version": "2.0.10638-1",
    "deps": {
      "jitsi-videobridge2": "2.3-260-gea11cd36c-1",
      "jicofo": "1.0-1167-1",
      "jitsi-meet-web": "1.0.8919-1",
      "jitsi-meet-web-config": "1.0.8919-1",
      "jitsi-meet-prosody": "1.0.8919-1"
    },
    "recommends": {
      "jitsi-meet-turnserver": "1.0.8919-1"
    }
  },
  {
    "version": "2.0.10637-1",
    "deps": {
      "jitsi-videobridge2": "2.3-260-gea11cd36c-1",
      "jicofo": "1.0-1167-1",
      "jitsi-meet-web": "1.0.8918-1",
      "jitsi-meet-web-config": "1.0.8918-1",
      "jitsi-meet-prosody": "1.0.8918-1"
    },
    "recommends": {
      "jitsi-meet-turnserver": "1.0.8918-1"
    }
  },
  {
    "version": "2.0.10636-1",
    "deps": {
      "jitsi-videobridge2": "2.3-260-gea11cd36c-1",
      "jicofo": "1.0-1166-1",
      "jitsi-meet-web": "1.0.8918-1",
      "jitsi-meet-web-config": "1.0.8918-1",
      "jitsi-meet-prosody": "1.0.8918-1"
    },
    "recommends": {
      "jitsi-meet-turnserver": "1.0.8918-1"
    }
  },
  {
    "version": "2.0.10635-1",
    "deps": {
      "jitsi-videobridge2": "2.3-260-gea11cd36c-1",
      "jicofo": "1.0-1166-1",
      "jitsi-meet-web": "1.0.8917-1",
      "jitsi-meet-web-config": "1.0.8917-1",
      "jitsi-meet-prosody": "1.0.8917-1"
    },
    "recommends": {
      "jitsi-meet-turnserver": "1.0.8917-1"
    }
  },
  {
    "version": "2.0.10634-1",
    "deps": {
      "jitsi-videobridge2": "2.3-260-gea11cd36c-1",
      "jicofo": "1.0-1166-1",
      "jitsi-meet-web": "1.0.8916-1",
      "jitsi-meet-web-config": "1.0.8916-1",
      "jitsi-meet-prosody": "1.0.8916-1"
    },
    "recommends": {
      "jitsi-meet-turnserver": "1.0.8916-1"
    }
  },
  {
    "version": "2.0.10633-1",
    "deps": {
      "jitsi-videobridge2": "2.3-260-gea11cd36c-1",
      "jicofo": "1.0-1166-1",
      "jitsi-meet-web": "1.0.8915-1",
      "jitsi-meet-web-config": "1.0.8915-1",
      "jitsi-meet-prosody": "1.0.8915-1"
    },
    "recommends": {
      "jitsi-meet-turnserver": "1.0.8915-1"
    }
  },
  {
    "version": "2.0.10632-1",
    "deps": {
      "jitsi-videobridge2": "2.3-260-gea11cd36c-1",
      "jicofo": "1.0-1165-1",
      "jitsi-meet-web": "1.0.8915-1",
      "jitsi-meet-web-config": "1.0.8915-1",
      "jitsi-meet-prosody": "1.0.8915-1"
    },
    "recommends": {
      "jitsi-meet-turnserver": "1.0.8915-1"
    }
  },
  {
    "version": "2.0.10631-1",
    "deps": {
      "jitsi-videobridge2": "2.3-260-gea11cd36c-1",
      "jicofo": "1.0-1165-1",
      "jitsi-meet-web": "1.0.8914-1",
      "jitsi-meet-web-config": "1.0.8914-1",
      "jitsi-meet-prosody": "1.0.8914-1"
    },
    "recommends": {
      "jitsi-meet-turnserver": "1.0.8914-1"
    }
  },
  {
    "version": "2.0.10630-1",
    "deps": {
      "jitsi-videobridge2": "2.3-260-gea11cd36c-1",
      "jicofo": "1.0-1165-1",
      "jitsi-meet-web": "1.0.8913-1",
      "jitsi-meet-web-config": "1.0.8913-1",
      "jitsi-meet-prosody": "1.0.8913-1"
    },
    "recommends": {
      "jitsi-meet-turnserver": "1.0.8913-1"
    }
  },
  {
    "version": "2.0.10629-1",
    "deps": {
      "jitsi-videobridge2": "2.3-260-gea11cd36c-1",
      "jicofo": "1.0-1165-1",
      "jitsi-meet-web": "1.0.8912-1",
      "jitsi-meet-web-config": "1.0.8912-1",
      "jitsi-meet-prosody": "1.0.8912-1"
    },
    "recommends": {
      "jitsi-meet-turnserver": "1.0.8912-1"
    }
  },
  {
    "version": "2.0.10628-1",
    "deps": {
      "jitsi-videobridge2": "2.3-260-gea11cd36c-1",
      "jicofo": "1.0-1165-1",
      "jitsi-meet-web": "1.0.8911-1",
      "jitsi-meet-web-config": "1.0.8911-1",
      "jitsi-meet-prosody": "1.0.8911-1"
    },
    "recommends": {
      "jitsi-meet-turnserver": "1.0.8911-1"
    }
  },
  {
    "version": "2.0.10627-1",
    "deps": {
      "jitsi-videobridge2": "2.3-260-gea11cd36c-1",
      "jicofo": "1.0-1165-1",
      "jitsi-meet-web": "1.0.8910-1",
      "jitsi-meet-web-config": "1.0.8910-1",
      "jitsi-meet-prosody": "1.0.8910-1"
    },
    "recommends": {
      "jitsi-meet-turnserver": "1.0.8910-1"
    }
  },
  {
    "version": "2.0.10626-1",
    "deps": {
      "jitsi-videobridge2": "2.3-260-gea11cd36c-1",
      "jicofo": "1.0-1165-1",
      "jitsi-meet-web": "1.0.8909-1",
      "jitsi-meet-web-config": "1.0.8909-1",
      "jitsi-meet-prosody": "1.0.8909-1"
    },
    "recommends": {
      "jitsi-meet-turnserver": "1.0.8909-1"
    }
  },
  {
    "version": "2.0.10625-1",
    "deps": {
      "jitsi-videobridge2": "2.3-260-gea11cd36c-1",
      "jicofo": "1.0-1165-1",
      "jitsi-meet-web": "1.0.8908-1",
      "jitsi-meet-web-config": "1.0.8908-1",
      "jitsi-meet-prosody": "1.0.8908-1"
    },
    "recommends": {
      "jitsi-meet-turnserver": "1.0.8908-1"
    }
  },
  {
    "version": "2.0.10624-1",
    "deps": {
      "jitsi-videobridge2": "2.3-260-gea11cd36c-1",
      "jicofo": "1.0-1164-1",
      "jitsi-meet-web": "1.0.8908-1",
      "jitsi-meet-web-config": "1.0.8908-1",
      "jitsi-meet-prosody": "1.0.8908-1"
    },
    "recommends": {
      "jitsi-meet-turnserver": "1.0.8908-1"
    }
  },
  {
    "version": "2.0.10623-1",
    "deps": {
      "jitsi-videobridge2": "2.3-260-gea11cd36c-1",
      "jicofo": "1.0-1164-1",
      "jitsi-meet-web": "1.0.8907-1",
      "jitsi-meet-web-config": "1.0.8907-1",
      "jitsi-meet-prosody": "1.0.8907-1"
    },
    "recommends": {
      "jitsi-meet-turnserver": "1.0.8907-1"
    }
  },
  {
    "version": "2.0.10622-1",
    "deps": {
      "jitsi-videobridge2": "2.3-260-gea11cd36c-1",
      "jicofo": "1.0-1164-1",
      "jitsi-meet-web": "1.0.8906-1",
      "jitsi-meet-web-config": "1.0.8906-1",
      "jitsi-meet-prosody": "1.0.8906-1"
    },
    "recommends": {
      "jitsi-meet-turnserver": "1.0.8906-1"
    }
  },
  {
    "version": "2.0.10621-1",
    "deps": {
      "jitsi-videobridge2": "2.3-260-gea11cd36c-1",
      "jicofo": "1.0-1164-1",
      "jitsi-meet-web": "1.0.8905-1",
      "jitsi-meet-web-config": "1.0.8905-1",
      "jitsi-meet-prosody": "1.0.8905-1"
    },
    "recommends": {
      "jitsi-meet-turnserver": "1.0.8905-1"
    }
  },
  {
    "version": "2.0.10620-1",
    "deps": {
      "jitsi-videobridge2": "2.3-260-gea11cd36c-1",
      "jicofo": "1.0-1164-1",
      "jitsi-meet-web": "1.0.8904-1",
      "jitsi-meet-web-config": "1.0.8904-1",
      "jitsi-meet-prosody": "1.0.8904-1"
    },
    "recommends": {
      "jitsi-meet-turnserver": "1.0.8904-1"
    }
  },
  {
    "version": "2.0.10619-1",
    "deps": {
      "jitsi-videobridge2": "2.3-260-gea11cd36c-1",
      "jicofo": "1.0-1164-1",
      "jitsi-meet-web": "1.0.8903-1",
      "jitsi-meet-web-config": "1.0.8903-1",
      "jitsi-meet-prosody": "1.0.8903-1"
    },
    "recommends": {
      "jitsi-meet-turnserver": "1.0.8903-1"
    }
  },
  {
    "version": "2.0.10618-1",
    "deps": {
      "jitsi-videobridge2": "2.3-260-gea11cd36c-1",
      "jicofo": "1.0-1164-1",
      "jitsi-meet-web": "1.0.8902-1",
      "jitsi-meet-web-config": "1.0.8902-1",
      "jitsi-meet-prosody": "1.0.8902-1"
    },
    "recommends": {
      "jitsi-meet-turnserver": "1.0.8902-1"
    }
  },
  {
    "version": "2.0.10617-1",
    "deps": {
      "jitsi-videobridge2": "2.3-260-gea11cd36c-1",
      "jicofo": "1.0-1164-1",
      "jitsi-meet-web": "1.0.8901-1",
      "jitsi-meet-web-config": "1.0.8901-1",
      "jitsi-meet-prosody": "1.0.8901-1"
    },
    "recommends": {
      "jitsi-meet-turnserver": "1.0.8901-1"
    }
  },
  {
    "version": "2.0.10616-1",
    "deps": {
      "jitsi-videobridge2": "2.3-260-gea11cd36c-1",
      "jicofo": "1.0-1164-1",
      "jitsi-meet-web": "1.0.8900-1",
      "jitsi-meet-web-config": "1.0.8900-1",
      "jitsi-meet-prosody": "1.0.8900-1"
    },
    "recommends": {
      "jitsi-meet-turnserver": "1.0.8900-1"
    }
  },
  {
    "version": "2.0.10615-1",
    "deps": {
      "jitsi-videobridge2": "2.3-260-gea11cd36c-1",
      "jicofo": "1.0-1163-1",
      "jitsi-meet-web": "1.0.8900-1",
      "jitsi-meet-web-config": "1.0.8900-1",
      "jitsi-meet-prosody": "1.0.8900-1"
    },
    "recommends": {
      "jitsi-meet-turnserver": "1.0.8900-1"
    }
  },
  {
    "version": "2.0.10614-1",
    "deps": {
      "jitsi-videobridge2": "2.3-260-gea11cd36c-1",
      "jicofo": "1.0-1163-1",
      "jitsi-meet-web": "1.0.8899-1",
      "jitsi-meet-web-config": "1.0.8899-1",
      "jitsi-meet-prosody": "1.0.8899-1"
    },
    "recommends": {
      "jitsi-meet-turnserver": "1.0.8899-1"
    }
  },
  {
    "version": "2.0.10613-1",
    "deps": {
      "jitsi-videobridge2": "2.3-260-gea11cd36c-1",
      "jicofo": "1.0-1163-1",
      "jitsi-meet-web": "1.0.8898-1",
      "jitsi-meet-web-config": "1.0.8898-1",
      "jitsi-meet-prosody": "1.0.8898-1"
    },
    "recommends": {
      "jitsi-meet-turnserver": "1.0.8898-1"
    }
  },
  {
    "version": "2.0.10612-1",
    "deps": {
      "jitsi-videobridge2": "2.3-260-gea11cd36c-1",
      "jicofo": "1.0-1163-1",
      "jitsi-meet-web": "1.0.8897-1",
      "jitsi-meet-web-config": "1.0.8897-1",
      "jitsi-meet-prosody": "1.0.8897-1"
    },
    "recommends": {
      "jitsi-meet-turnserver": "1.0.8897-1"
    }
  },
  {
    "version": "2.0.10611-1",
    "deps": {
      "jitsi-videobridge2": "2.3-260-gea11cd36c-1",
      "jicofo": "1.0-1162-1",
      "jitsi-meet-web": "1.0.8897-1",
      "jitsi-meet-web-config": "1.0.8897-1",
      "jitsi-meet-prosody": "1.0.8897-1"
    },
    "recommends": {
      "jitsi-meet-turnserver": "1.0.8897-1"
    }
  },
  {
    "version": "2.0.10610-1",
    "deps": {
      "jitsi-videobridge2": "2.3-260-gea11cd36c-1",
      "jicofo": "1.0-1162-1",
      "jitsi-meet-web": "1.0.8896-1",
      "jitsi-meet-web-config": "1.0.8896-1",
      "jitsi-meet-prosody": "1.0.8896-1"
    },
    "recommends": {
      "jitsi-meet-turnserver": "1.0.8896-1"
    }
  },
  {
    "version": "2.0.10609-1",
    "deps": {
      "jitsi-videobridge2": "2.3-260-gea11cd36c-1",
      "jicofo": "1.0-1162-1",
      "jitsi-meet-web": "1.0.8895-1",
      "jitsi-meet-web-config": "1.0.8895-1",
      "jitsi-meet-prosody": "1.0.8895-1"
    },
    "recommends": {
      "jitsi-meet-turnserver": "1.0.8895-1"
    }
  },
  {
    "version": "2.0.10608-1",
    "deps": {
      "jitsi-videobridge2": "2.3-259-g22868ff7d-1",
      "jicofo": "1.0-1162-1",
      "jitsi-meet-web": "1.0.8895-1",
      "jitsi-meet-web-config": "1.0.8895-1",
      "jitsi-meet-prosody": "1.0.8895-1"
    },
    "recommends": {
      "jitsi-meet-turnserver": "1.0.8895-1"
    }
  },
  {
    "version": "2.0.10607-1",
    "deps": {
      "jitsi-videobridge2": "2.3-259-g22868ff7d-1",
      "jicofo": "1.0-1162-1",
      "jitsi-meet-web": "1.0.8894-1",
      "jitsi-meet-web-config": "1.0.8894-1",
      "jitsi-meet-prosody": "1.0.8894-1"
    },
    "recommends": {
      "jitsi-meet-turnserver": "1.0.8894-1"
    }
  },
  {
    "version": "2.0.10606-1",
    "deps": {
      "jitsi-videobridge2": "2.3-259-g22868ff7d-1",
      "jicofo": "1.0-1162-1",
      "jitsi-meet-web": "1.0.8893-1",
      "jitsi-meet-web-config": "1.0.8893-1",
      "jitsi-meet-prosody": "1.0.8893-1"
    },
    "recommends": {
      "jitsi-meet-turnserver": "1.0.8893-1"
    }
  },
  {
    "version": "2.0.10605-1",
    "deps": {
      "jitsi-videobridge2": "2.3-259-g22868ff7d-1",
      "jicofo": "1.0-1162-1",
      "jitsi-meet-web": "1.0.8892-1",
      "jitsi-meet-web-config": "1.0.8892-1",
      "jitsi-meet-prosody": "1.0.8892-1"
    },
    "recommends": {
      "jitsi-meet-turnserver": "1.0.8892-1"
    }
  },
  {
    "version": "2.0.10604-1",
    "deps": {
      "jitsi-videobridge2": "2.3-259-g22868ff7d-1",
      "jicofo": "1.0-1162-1",
      "jitsi-meet-web": "1.0.8891-1",
      "jitsi-meet-web-config": "1.0.8891-1",
      "jitsi-meet-prosody": "1.0.8891-1"
    },
    "recommends": {
      "jitsi-meet-turnserver": "1.0.8891-1"
    }
  },
  {
    "version": "2.0.10603-1",
    "deps": {
      "jitsi-videobridge2": "2.3-259-g22868ff7d-1",
      "jicofo": "1.0-1162-1",
      "jitsi-meet-web": "1.0.8890-1",
      "jitsi-meet-web-config": "1.0.8890-1",
      "jitsi-meet-prosody": "1.0.8890-1"
    },
    "recommends": {
      "jitsi-meet-turnserver": "1.0.8890-1"
    }
  },
  {
    "version": "2.0.10602-1",
    "deps": {
      "jitsi-videobridge2": "2.3-259-g22868ff7d-1",
      "jicofo": "1.0-1162-1",
      "jitsi-meet-web": "1.0.8889-1",
      "jitsi-meet-web-config": "1.0.8889-1",
      "jitsi-meet-prosody": "1.0.8889-1"
    },
    "recommends": {
      "jitsi-meet-turnserver": "1.0.8889-1"
    }
  },
  {
    "version": "2.0.10601-1",
    "deps": {
      "jitsi-videobridge2": "2.3-259-g22868ff7d-1",
      "jicofo": "1.0-1162-1",
      "jitsi-meet-web": "1.0.8888-1",
      "jitsi-meet-web-config": "1.0.8888-1",
      "jitsi-meet-prosody": "1.0.8888-1"
    },
    "recommends": {
      "jitsi-meet-turnserver": "1.0.8888-1"
    }
  },
  {
    "version": "2.0.10600-1",
    "deps": {
      "jitsi-videobridge2": "2.3-259-g22868ff7d-1",
      "jicofo": "1.0-1162-1",
      "jitsi-meet-web": "1.0.8887-1",
      "jitsi-meet-web-config": "1.0.8887-1",
      "jitsi-meet-prosody": "1.0.8887-1"
    },
    "recommends": {
      "jitsi-meet-turnserver": "1.0.8887-1"
    }
  },
  {
    "version": "2.0.10599-1",
    "deps": {
      "jitsi-videobridge2": "2.3-259-g22868ff7d-1",
      "jicofo": "1.0-1162-1",
      "jitsi-meet-web": "1.0.8886-1",
      "jitsi-meet-web-config": "1.0.8886-1",
      "jitsi-meet-prosody": "1.0.8886-1"
    },
    "recommends": {
      "jitsi-meet-turnserver": "1.0.8886-1"
    }
  },
  {
    "version": "2.0.10598-1",
    "deps": {
      "jitsi-videobridge2": "2.3-259-g22868ff7d-1",
      "jicofo": "1.0-1162-1",
      "jitsi-meet-web": "1.0.8885-1",
      "jitsi-meet-web-config": "1.0.8885-1",
      "jitsi-meet-prosody": "1.0.8885-1"
    },
    "recommends": {
      "jitsi-meet-turnserver": "1.0.8885-1"
    }
  },
  {
    "version": "2.0.10597-1",
    "deps": {
      "jitsi-videobridge2": "2.3-259-g22868ff7d-1",
      "jicofo": "1.0-1162-1",
      "jitsi-meet-web": "1.0.8884-1",
      "jitsi-meet-web-config": "1.0.8884-1",
      "jitsi-meet-prosody": "1.0.8884-1"
    },
    "recommends": {
      "jitsi-meet-turnserver": "1.0.8884-1"
    }
  },
  {
    "version": "2.0.10596-1",
    "deps": {
      "jitsi-videobridge2": "2.3-259-g22868ff7d-1",
      "jicofo": "1.0-1162-1",
      "jitsi-meet-web": "1.0.8883-1",
      "jitsi-meet-web-config": "1.0.8883-1",
      "jitsi-meet-prosody": "1.0.8883-1"
    },
    "recommends": {
      "jitsi-meet-turnserver": "1.0.8883-1"
    }
  },
  {
    "version": "2.0.10595-1",
    "deps": {
      "jitsi-videobridge2": "2.3-259-g22868ff7d-1",
      "jicofo": "1.0-1162-1",
      "jitsi-meet-web": "1.0.8882-1",
      "jitsi-meet-web-config": "1.0.8882-1",
      "jitsi-meet-prosody": "1.0.8882-1"
    },
    "recommends": {
      "jitsi-meet-turnserver": "1.0.8882-1"
    }
  },
  {
    "version": "2.0.10594-1",
    "deps": {
      "jitsi-videobridge2": "2.3-259-g22868ff7d-1",
      "jicofo": "1.0-1162-1",
      "jitsi-meet-web": "1.0.8881-1",
      "jitsi-meet-web-config": "1.0.8881-1",
      "jitsi-meet-prosody": "1.0.8881-1"
    },
    "recommends": {
      "jitsi-meet-turnserver": "1.0.8881-1"
    }
  },
  {
    "version": "2.0.10593-1",
    "deps": {
      "jitsi-videobridge2": "2.3-259-g22868ff7d-1",
      "jicofo": "1.0-1162-1",
      "jitsi-meet-web": "1.0.8880-1",
      "jitsi-meet-web-config": "1.0.8880-1",
      "jitsi-meet-prosody": "1.0.8880-1"
    },
    "recommends": {
      "jitsi-meet-turnserver": "1.0.8880-1"
    }
  },
  {
    "version": "2.0.10592-1",
    "deps": {
      "jitsi-videobridge2": "2.3-259-g22868ff7d-1",
      "jicofo": "1.0-1162-1",
      "jitsi-meet-web": "1.0.8879-1",
      "jitsi-meet-web-config": "1.0.8879-1",
      "jitsi-meet-prosody": "1.0.8879-1"
    },
    "recommends": {
      "jitsi-meet-turnserver": "1.0.8879-1"
    }
  },
  {
    "version": "2.0.10591-1",
    "deps": {
      "jitsi-videobridge2": "2.3-259-g22868ff7d-1",
      "jicofo": "1.0-1162-1",
      "jitsi-meet-web": "1.0.8878-1",
      "jitsi-meet-web-config": "1.0.8878-1",
      "jitsi-meet-prosody": "1.0.8878-1"
    },
    "recommends": {
      "jitsi-meet-turnserver": "1.0.8878-1"
    }
  },
  {
    "version": "2.0.10590-1",
    "deps": {
      "jitsi-videobridge2": "2.3-259-g22868ff7d-1",
      "jicofo": "1.0-1162-1",
      "jitsi-meet-web": "1.0.8877-1",
      "jitsi-meet-web-config": "1.0.8877-1",
      "jitsi-meet-prosody": "1.0.8877-1"
    },
    "recommends": {
      "jitsi-meet-turnserver": "1.0.8877-1"
    }
  },
  {
    "version": "2.0.10589-1",
    "deps": {
      "jitsi-videobridge2": "2.3-259-g22868ff7d-1",
      "jicofo": "1.0-1162-1",
      "jitsi-meet-web": "1.0.8876-1",
      "jitsi-meet-web-config": "1.0.8876-1",
      "jitsi-meet-prosody": "1.0.8876-1"
    },
    "recommends": {
      "jitsi-meet-turnserver": "1.0.8876-1"
    }
  },
  {
    "version": "2.0.10588-1",
    "deps": {
      "jitsi-videobridge2": "2.3-259-g22868ff7d-1",
      "jicofo": "1.0-1162-1",
      "jitsi-meet-web": "1.0.8875-1",
      "jitsi-meet-web-config": "1.0.8875-1",
      "jitsi-meet-prosody": "1.0.8875-1"
    },
    "recommends": {
      "jitsi-meet-turnserver": "1.0.8875-1"
    }
  },
  {
    "version": "2.0.10587-1",
    "deps": {
      "jitsi-videobridge2": "2.3-259-g22868ff7d-1",
      "jicofo": "1.0-1162-1",
      "jitsi-meet-web": "1.0.8874-1",
      "jitsi-meet-web-config": "1.0.8874-1",
      "jitsi-meet-prosody": "1.0.8874-1"
    },
    "recommends": {
      "jitsi-meet-turnserver": "1.0.8874-1"
    }
  },
  {
    "version": "2.0.10586-1",
    "deps": {
      "jitsi-videobridge2": "2.3-259-g22868ff7d-1",
      "jicofo": "1.0-1162-1",
      "jitsi-meet-web": "1.0.8873-1",
      "jitsi-meet-web-config": "1.0.8873-1",
      "jitsi-meet-prosody": "1.0.8873-1"
    },
    "recommends": {
      "jitsi-meet-turnserver": "1.0.8873-1"
    }
  },
  {
    "version": "2.0.10585-1",
    "deps": {
      "jitsi-videobridge2": "2.3-259-g22868ff7d-1",
      "jicofo": "1.0-1162-1",
      "jitsi-meet-web": "1.0.8872-1",
      "jitsi-meet-web-config": "1.0.8872-1",
      "jitsi-meet-prosody": "1.0.8872-1"
    },
    "recommends": {
      "jitsi-meet-turnserver": "1.0.8872-1"
    }
  },
  {
    "version": "2.0.10584-1",
    "deps": {
      "jitsi-videobridge2": "2.3-259-g22868ff7d-1",
      "jicofo": "1.0-1162-1",
      "jitsi-meet-web": "1.0.8871-1",
      "jitsi-meet-web-config": "1.0.8871-1",
      "jitsi-meet-prosody": "1.0.8871-1"
    },
    "recommends": {
      "jitsi-meet-turnserver": "1.0.8871-1"
    }
  },
  {
    "version": "2.0.10583-1",
    "deps": {
      "jitsi-videobridge2": "2.3-259-g22868ff7d-1",
      "jicofo": "1.0-1162-1",
      "jitsi-meet-web": "1.0.8870-1",
      "jitsi-meet-web-config": "1.0.8870-1",
      "jitsi-meet-prosody": "1.0.8870-1"
    },
    "recommends": {
      "jitsi-meet-turnserver": "1.0.8870-1"
    }
  },
  {
    "version": "2.0.10582-1",
    "deps": {
      "jitsi-videobridge2": "2.3-259-g22868ff7d-1",
      "jicofo": "1.0-1162-1",
      "jitsi-meet-web": "1.0.8869-1",
      "jitsi-meet-web-config": "1.0.8869-1",
      "jitsi-meet-prosody": "1.0.8869-1"
    },
    "recommends": {
      "jitsi-meet-turnserver": "1.0.8869-1"
    }
  },
  {
    "version": "2.0.10581-1",
    "deps": {
      "jitsi-videobridge2": "2.3-259-g22868ff7d-1",
      "jicofo": "1.0-1162-1",
      "jitsi-meet-web": "1.0.8868-1",
      "jitsi-meet-web-config": "1.0.8868-1",
      "jitsi-meet-prosody": "1.0.8868-1"
    },
    "recommends": {
      "jitsi-meet-turnserver": "1.0.8868-1"
    }
  },
  {
    "version": "2.0.10580-1",
    "deps": {
      "jitsi-videobridge2": "2.3-259-g22868ff7d-1",
      "jicofo": "1.0-1161-1",
      "jitsi-meet-web": "1.0.8868-1",
      "jitsi-meet-web-config": "1.0.8868-1",
      "jitsi-meet-prosody": "1.0.8868-1"
    },
    "recommends": {
      "jitsi-meet-turnserver": "1.0.8868-1"
    }
  },
  {
    "version": "2.0.10579-1",
    "deps": {
      "jitsi-videobridge2": "2.3-259-g22868ff7d-1",
      "jicofo": "1.0-1161-1",
      "jitsi-meet-web": "1.0.8867-1",
      "jitsi-meet-web-config": "1.0.8867-1",
      "jitsi-meet-prosody": "1.0.8867-1"
    },
    "recommends": {
      "jitsi-meet-turnserver": "1.0.8867-1"
    }
  },
  {
    "version": "2.0.10578-1",
    "deps": {
      "jitsi-videobridge2": "2.3-259-g22868ff7d-1",
      "jicofo": "1.0-1161-1",
      "jitsi-meet-web": "1.0.8866-1",
      "jitsi-meet-web-config": "1.0.8866-1",
      "jitsi-meet-prosody": "1.0.8866-1"
    },
    "recommends": {
      "jitsi-meet-turnserver": "1.0.8866-1"
    }
  },
  {
    "version": "2.0.10577-1",
    "deps": {
      "jitsi-videobridge2": "2.3-259-g22868ff7d-1",
      "jicofo": "1.0-1161-1",
      "jitsi-meet-web": "1.0.8865-1",
      "jitsi-meet-web-config": "1.0.8865-1",
      "jitsi-meet-prosody": "1.0.8865-1"
    },
    "recommends": {
      "jitsi-meet-turnserver": "1.0.8865-1"
    }
  },
  {
    "version": "2.0.10576-1",
    "deps": {
      "jitsi-videobridge2": "2.3-259-g22868ff7d-1",
      "jicofo": "1.0-1161-1",
      "jitsi-meet-web": "1.0.8864-1",
      "jitsi-meet-web-config": "1.0.8864-1",
      "jitsi-meet-prosody": "1.0.8864-1"
    },
    "recommends": {
      "jitsi-meet-turnserver": "1.0.8864-1"
    }
  },
  {
    "version": "2.0.10575-1",
    "deps": {
      "jitsi-videobridge2": "2.3-259-g22868ff7d-1",
      "jicofo": "1.0-1161-1",
      "jitsi-meet-web": "1.0.8863-1",
      "jitsi-meet-web-config": "1.0.8863-1",
      "jitsi-meet-prosody": "1.0.8863-1"
    },
    "recommends": {
      "jitsi-meet-turnserver": "1.0.8863-1"
    }
  },
  {
    "version": "2.0.10574-1",
    "deps": {
      "jitsi-videobridge2": "2.3-259-g22868ff7d-1",
      "jicofo": "1.0-1161-1",
      "jitsi-meet-web": "1.0.8862-1",
      "jitsi-meet-web-config": "1.0.8862-1",
      "jitsi-meet-prosody": "1.0.8862-1"
    },
    "recommends": {
      "jitsi-meet-turnserver": "1.0.8862-1"
    }
  },
  {
    "version": "2.0.10573-1",
    "deps": {
      "jitsi-videobridge2": "2.3-259-g22868ff7d-1",
      "jicofo": "1.0-1161-1",
      "jitsi-meet-web": "1.0.8861-1",
      "jitsi-meet-web-config": "1.0.8861-1",
      "jitsi-meet-prosody": "1.0.8861-1"
    },
    "recommends": {
      "jitsi-meet-turnserver": "1.0.8861-1"
    }
  },
  {
    "version": "2.0.10572-1",
    "deps": {
      "jitsi-videobridge2": "2.3-259-g22868ff7d-1",
      "jicofo": "1.0-1161-1",
      "jitsi-meet-web": "1.0.8860-1",
      "jitsi-meet-web-config": "1.0.8860-1",
      "jitsi-meet-prosody": "1.0.8860-1"
    },
    "recommends": {
      "jitsi-meet-turnserver": "1.0.8860-1"
    }
  },
  {
    "version": "2.0.10571-1",
    "deps": {
      "jitsi-videobridge2": "2.3-259-g22868ff7d-1",
      "jicofo": "1.0-1161-1",
      "jitsi-meet-web": "1.0.8859-1",
      "jitsi-meet-web-config": "1.0.8859-1",
      "jitsi-meet-prosody": "1.0.8859-1"
    },
    "recommends": {
      "jitsi-meet-turnserver": "1.0.8859-1"
    }
  },
  {
    "version": "2.0.10570-1",
    "deps": {
      "jitsi-videobridge2": "2.3-259-g22868ff7d-1",
      "jicofo": "1.0-1161-1",
      "jitsi-meet-web": "1.0.8858-1",
      "jitsi-meet-web-config": "1.0.8858-1",
      "jitsi-meet-prosody": "1.0.8858-1"
    },
    "recommends": {
      "jitsi-meet-turnserver": "1.0.8858-1"
    }
  },
  {
    "version": "2.0.10569-1",
    "deps": {
      "jitsi-videobridge2": "2.3-259-g22868ff7d-1",
      "jicofo": "1.0-1161-1",
      "jitsi-meet-web": "1.0.8857-1",
      "jitsi-meet-web-config": "1.0.8857-1",
      "jitsi-meet-prosody": "1.0.8857-1"
    },
    "recommends": {
      "jitsi-meet-turnserver": "1.0.8857-1"
    }
  },
  {
    "version": "2.0.10568-1",
    "deps": {
      "jitsi-videobridge2": "2.3-259-g22868ff7d-1",
      "jicofo": "1.0-1161-1",
      "jitsi-meet-web": "1.0.8856-1",
      "jitsi-meet-web-config": "1.0.8856-1",
      "jitsi-meet-prosody": "1.0.8856-1"
    },
    "recommends": {
      "jitsi-meet-turnserver": "1.0.8856-1"
    }
  },
  {
    "version": "2.0.10567-1",
    "deps": {
      "jitsi-videobridge2": "2.3-259-g22868ff7d-1",
      "jicofo": "1.0-1161-1",
      "jitsi-meet-web": "1.0.8855-1",
      "jitsi-meet-web-config": "1.0.8855-1",
      "jitsi-meet-prosody": "1.0.8855-1"
    },
    "recommends": {
      "jitsi-meet-turnserver": "1.0.8855-1"
    }
  },
  {
    "version": "2.0.10566-1",
    "deps": {
      "jitsi-videobridge2": "2.3-259-g22868ff7d-1",
      "jicofo": "1.0-1161-1",
      "jitsi-meet-web": "1.0.8854-1",
      "jitsi-meet-web-config": "1.0.8854-1",
      "jitsi-meet-prosody": "1.0.8854-1"
    },
    "recommends": {
      "jitsi-meet-turnserver": "1.0.8854-1"
    }
  },
  {
    "version": "2.0.10565-1",
    "deps": {
      "jitsi-videobridge2": "2.3-259-g22868ff7d-1",
      "jicofo": "1.0-1161-1",
      "jitsi-meet-web": "1.0.8853-1",
      "jitsi-meet-web-config": "1.0.8853-1",
      "jitsi-meet-prosody": "1.0.8853-1"
    },
    "recommends": {
      "jitsi-meet-turnserver": "1.0.8853-1"
    }
  },
  {
    "version": "2.0.10564-1",
    "deps": {
      "jitsi-videobridge2": "2.3-259-g22868ff7d-1",
      "jicofo": "1.0-1161-1",
      "jitsi-meet-web": "1.0.8852-1",
      "jitsi-meet-web-config": "1.0.8852-1",
      "jitsi-meet-prosody": "1.0.8852-1"
    },
    "recommends": {
      "jitsi-meet-turnserver": "1.0.8852-1"
    }
  },
  {
    "version": "2.0.10563-1",
    "deps": {
      "jitsi-videobridge2": "2.3-259-g22868ff7d-1",
      "jicofo": "1.0-1161-1",
      "jitsi-meet-web": "1.0.8851-1",
      "jitsi-meet-web-config": "1.0.8851-1",
      "jitsi-meet-prosody": "1.0.8851-1"
    },
    "recommends": {
      "jitsi-meet-turnserver": "1.0.8851-1"
    }
  },
  {
    "version": "2.0.10562-1",
    "deps": {
      "jitsi-videobridge2": "2.3-259-g22868ff7d-1",
      "jicofo": "1.0-1161-1",
      "jitsi-meet-web": "1.0.8850-1",
      "jitsi-meet-web-config": "1.0.8850-1",
      "jitsi-meet-prosody": "1.0.8850-1"
    },
    "recommends": {
      "jitsi-meet-turnserver": "1.0.8850-1"
    }
  },
  {
    "version": "2.0.10561-1",
    "deps": {
      "jitsi-videobridge2": "2.3-259-g22868ff7d-1",
      "jicofo": "1.0-1161-1",
      "jitsi-meet-web": "1.0.8849-1",
      "jitsi-meet-web-config": "1.0.8849-1",
      "jitsi-meet-prosody": "1.0.8849-1"
    },
    "recommends": {
      "jitsi-meet-turnserver": "1.0.8849-1"
    }
  },
  {
    "version": "2.0.10560-1",
    "deps": {
      "jitsi-videobridge2": "2.3-259-g22868ff7d-1",
      "jicofo": "1.0-1161-1",
      "jitsi-meet-web": "1.0.8848-1",
      "jitsi-meet-web-config": "1.0.8848-1",
      "jitsi-meet-prosody": "1.0.8848-1"
    },
    "recommends": {
      "jitsi-meet-turnserver": "1.0.8848-1"
    }
  },
  {
    "version": "2.0.10559-1",
    "deps": {
      "jitsi-videobridge2": "2.3-259-g22868ff7d-1",
      "jicofo": "1.0-1161-1",
      "jitsi-meet-web": "1.0.8847-1",
      "jitsi-meet-web-config": "1.0.8847-1",
      "jitsi-meet-prosody": "1.0.8847-1"
    },
    "recommends": {
      "jitsi-meet-turnserver": "1.0.8847-1"
    }
  },
  {
    "version": "2.0.10558-1",
    "deps": {
      "jitsi-videobridge2": "2.3-259-g22868ff7d-1",
      "jicofo": "1.0-1161-1",
      "jitsi-meet-web": "1.0.8846-1",
      "jitsi-meet-web-config": "1.0.8846-1",
      "jitsi-meet-prosody": "1.0.8846-1"
    },
    "recommends": {
      "jitsi-meet-turnserver": "1.0.8846-1"
    }
  },
  {
    "version": "2.0.10557-1",
    "deps": {
      "jitsi-videobridge2": "2.3-259-g22868ff7d-1",
      "jicofo": "1.0-1161-1",
      "jitsi-meet-web": "1.0.8845-1",
      "jitsi-meet-web-config": "1.0.8845-1",
      "jitsi-meet-prosody": "1.0.8845-1"
    },
    "recommends": {
      "jitsi-meet-turnserver": "1.0.8845-1"
    }
  },
  {
    "version": "2.0.10556-1",
    "deps": {
      "jitsi-videobridge2": "2.3-259-g22868ff7d-1",
      "jicofo": "1.0-1161-1",
      "jitsi-meet-web": "1.0.8844-1",
      "jitsi-meet-web-config": "1.0.8844-1",
      "jitsi-meet-prosody": "1.0.8844-1"
    },
    "recommends": {
      "jitsi-meet-turnserver": "1.0.8844-1"
    }
  },
  {
    "version": "2.0.10555-1",
    "deps": {
      "jitsi-videobridge2": "2.3-259-g22868ff7d-1",
      "jicofo": "1.0-1161-1",
      "jitsi-meet-web": "1.0.8843-1",
      "jitsi-meet-web-config": "1.0.8843-1",
      "jitsi-meet-prosody": "1.0.8843-1"
    },
    "recommends": {
      "jitsi-meet-turnserver": "1.0.8843-1"
    }
  },
  {
    "version": "2.0.10554-1",
    "deps": {
      "jitsi-videobridge2": "2.3-259-g22868ff7d-1",
      "jicofo": "1.0-1161-1",
      "jitsi-meet-web": "1.0.8842-1",
      "jitsi-meet-web-config": "1.0.8842-1",
      "jitsi-meet-prosody": "1.0.8842-1"
    },
    "recommends": {
      "jitsi-meet-turnserver": "1.0.8842-1"
    }
  },
  {
    "version": "2.0.10553-1",
    "deps": {
      "jitsi-videobridge2": "2.3-259-g22868ff7d-1",
      "jicofo": "1.0-1161-1",
      "jitsi-meet-web": "1.0.8841-1",
      "jitsi-meet-web-config": "1.0.8841-1",
      "jitsi-meet-prosody": "1.0.8841-1"
    },
    "recommends": {
      "jitsi-meet-turnserver": "1.0.8841-1"
    }
  },
  {
    "version": "2.0.10552-1",
    "deps": {
      "jitsi-videobridge2": "2.3-259-g22868ff7d-1",
      "jicofo": "1.0-1161-1",
      "jitsi-meet-web": "1.0.8840-1",
      "jitsi-meet-web-config": "1.0.8840-1",
      "jitsi-meet-prosody": "1.0.8840-1"
    },
    "recommends": {
      "jitsi-meet-turnserver": "1.0.8840-1"
    }
  },
  {
    "version": "2.0.10551-1",
    "deps": {
      "jitsi-videobridge2": "2.3-259-g22868ff7d-1",
      "jicofo": "1.0-1161-1",
      "jitsi-meet-web": "1.0.8839-1",
      "jitsi-meet-web-config": "1.0.8839-1",
      "jitsi-meet-prosody": "1.0.8839-1"
    },
    "recommends": {
      "jitsi-meet-turnserver": "1.0.8839-1"
    }
  },
  {
    "version": "2.0.10550-1",
    "deps": {
      "jitsi-videobridge2": "2.3-259-g22868ff7d-1",
      "jicofo": "1.0-1161-1",
      "jitsi-meet-web": "1.0.8838-1",
      "jitsi-meet-web-config": "1.0.8838-1",
      "jitsi-meet-prosody": "1.0.8838-1"
    },
    "recommends": {
      "jitsi-meet-turnserver": "1.0.8838-1"
    }
  },
  {
    "version": "2.0.10549-1",
    "deps": {
      "jitsi-videobridge2": "2.3-259-g22868ff7d-1",
      "jicofo": "1.0-1161-1",
      "jitsi-meet-web": "1.0.8837-1",
      "jitsi-meet-web-config": "1.0.8837-1",
      "jitsi-meet-prosody": "1.0.8837-1"
    },
    "recommends": {
      "jitsi-meet-turnserver": "1.0.8837-1"
    }
  },
  {
    "version": "2.0.10548-1",
    "deps": {
      "jitsi-videobridge2": "2.3-259-g22868ff7d-1",
      "jicofo": "1.0-1161-1",
      "jitsi-meet-web": "1.0.8836-1",
      "jitsi-meet-web-config": "1.0.8836-1",
      "jitsi-meet-prosody": "1.0.8836-1"
    },
    "recommends": {
      "jitsi-meet-turnserver": "1.0.8836-1"
    }
  },
  {
    "version": "2.0.10547-1",
    "deps": {
      "jitsi-videobridge2": "2.3-259-g22868ff7d-1",
      "jicofo": "1.0-1161-1",
      "jitsi-meet-web": "1.0.8835-1",
      "jitsi-meet-web-config": "1.0.8835-1",
      "jitsi-meet-prosody": "1.0.8835-1"
    },
    "recommends": {
      "jitsi-meet-turnserver": "1.0.8835-1"
    }
  },
  {
    "version": "2.0.10546-1",
    "deps": {
      "jitsi-videobridge2": "2.3-259-g22868ff7d-1",
      "jicofo": "1.0-1161-1",
      "jitsi-meet-web": "1.0.8834-1",
      "jitsi-meet-web-config": "1.0.8834-1",
      "jitsi-meet-prosody": "1.0.8834-1"
    },
    "recommends": {
      "jitsi-meet-turnserver": "1.0.8834-1"
    }
  },
  {
    "version": "2.0.10545-1",
    "deps": {
      "jitsi-videobridge2": "2.3-259-g22868ff7d-1",
      "jicofo": "1.0-1161-1",
      "jitsi-meet-web": "1.0.8833-1",
      "jitsi-meet-web-config": "1.0.8833-1",
      "jitsi-meet-prosody": "1.0.8833-1"
    },
    "recommends": {
      "jitsi-meet-turnserver": "1.0.8833-1"
    }
  }
]